{"head": {"vars": ["var1", "var3"]}, "results": {"bindings": [{"var1": {"type": "uri", "value": "http://www.wikidata.org/entity/Q6004485"}, "var3": {"datatype": "http://www.w3.org/2001/XMLSchema#integer", "type": "literal", "value": "5"}}, {"var1": {"type": "uri", "value": "http://www.wikidata.org/entity/Q18631868"}, "var3": {"datatype": "http://www.w3.org/2001/XMLSchema#integer", "type": "literal", "value": "1"}}, {"var1": {"type": "uri", "value": "http://www.wikidata.org/entity/Q55599966"}, "var3": {"datatype": "http://www.w3.org/2001/XMLSchema#integer", "type": "literal", "value": "1"}}, {"var1": {"type": "uri", "value": "http://www.wikidata.org/entity/Q94317578"}, "var3": {"datatype": "http://www.w3.org/2001/XMLSchema#integer", "type": "literal", "value": "1"}}, {"var1": {"type": "uri", "value": "http://www.wikidata.org/entity/Q78403191"}, "var3": {"datatype": "http://www.w3.org/2001/XMLSchema#integer", "type": "literal", "value": "0"}}, {"var1": {"type": "uri", "value": "http://www.wikidata.org/entity/Q133286025"}, "var3": {"datatype": "http://www.w3.org/2001/XMLSchema#integer", "type": "literal", "value": "0"}}, {"var1": {"type": "uri", "value": "http://www.wikidata.org/entity/Q135975115"}, "var3": {"datatype": "http://www.w3.org/2001/XMLSchema#integer", "type": "literal", "value": "0"}}]}}